ndpretty/__init__.py
ndpretty/_nbdev.py
ndpretty/core.py
ndpretty-0.0.7.dist-info/METADATA
ndpretty-0.0.7.dist-info/WHEEL
ndpretty-0.0.7.dist-info/entry_points.txt
ndpretty-0.0.7.dist-info/top_level.txt
ndpretty-0.0.7.dist-info/RECORD
