Metadata-Version: 2.1
Name: ndpretty
Version: 0.0.7
Summary: Display numpy ndarrays in a pretty table in Jupyter notebooks
Home-page: https://github.com/deutschmn/ndpretty/tree/master/
Author: Patrick Deutschmann
Author-email: patrick@deutschmann.xyz
License: Apache Software License 2.0
Keywords: python
Platform: UNKNOWN
Classifier: Development Status :: 3 - Alpha
Classifier: Intended Audience :: Developers
Classifier: License :: OSI Approved :: Apache Software License
Classifier: Natural Language :: English
Classifier: Programming Language :: Python :: 3.6
Classifier: Programming Language :: Python :: 3.7
Classifier: Programming Language :: Python :: 3.8
Requires-Python: >=3.6
Requires-Dist: numpy
Requires-Dist: IPython
Requires-Dist: ipywidgets
Provides-Extra: dev
Requires-Dist: pandas ; extra == 'dev'
Requires-Dist: matplotlib ; extra == 'dev'
Requires-Dist: torch ; extra == 'dev'
Requires-Dist: seaborn ; extra == 'dev'
